dask_memusage_gpus/__init__.py
dask_memusage_gpus/definitions.py
dask_memusage_gpus/gpu_handler.py
dask_memusage_gpus/plugin.py
dask_memusage_gpus/utils.py
dask_memusage_gpus_plugin.py
dask_memusage_gpus-1.0.1.dist-info/LICENSE
dask_memusage_gpus-1.0.1.dist-info/METADATA
dask_memusage_gpus-1.0.1.dist-info/WHEEL
dask_memusage_gpus-1.0.1.dist-info/RECORD
