Metadata-Version: 2.1
Name: dask-memusage-gpus
Version: 1.0.1
Summary: A Dask Scheduler Plugin to monitor GPU memory usage for tasks
Home-page: https://github.com/discovery-unicamp/dask-memusage-gpus
License: MIT
Author: Julio Faracco
Author-email: jcfaracco@gmail.com
Maintainer: Julio Faracco
Maintainer-email: jcfaracco@gmail.com
Classifier: Development Status :: 1 - Planning
Classifier: Environment :: GPU :: NVIDIA CUDA
Classifier: Intended Audience :: Developers
Classifier: Intended Audience :: Science/Research
Classifier: License :: OSI Approved :: MIT License
Classifier: Operating System :: OS Independent
Classifier: Programming Language :: Python :: 2
Classifier: Programming Language :: Python :: 2.7
Classifier: Programming Language :: Python :: 3
Classifier: Programming Language :: Python :: 3.4
Classifier: Programming Language :: Python :: 3.5
Classifier: Programming Language :: Python :: 3.6
Classifier: Programming Language :: Python :: 3.7
Classifier: Programming Language :: Python :: 3.8
Classifier: Programming Language :: Python :: 3.9
Classifier: Programming Language :: Python :: 3.10
Classifier: Programming Language :: Python :: 3.11
Classifier: Programming Language :: Python :: 3.12
Requires-Dist: dask
Requires-Dist: distributed
Requires-Dist: lxml
Requires-Dist: openpyxl
Requires-Dist: pandas
Requires-Dist: pyarrow
Project-URL: Repository, https://github.com/discovery-unicamp/dask-memusage-gpus
